refinire/__init__.py
refinire/cli.py
refinire/py.typed
refinire/templates.py
refinire/tools.py
refinire/agents/__init__.py
refinire/agents/clarify_agent.py
refinire/agents/context_provider.py
refinire/agents/context_provider_factory.py
refinire/agents/evaluation_agent.py
refinire/agents/extractor.py
refinire/agents/notification.py
refinire/agents/router.py
refinire/agents/routing_agent.py
refinire/agents/validator.py
refinire/agents/flow/__init__.py
refinire/agents/flow/context.py
refinire/agents/flow/flow.py
refinire/agents/flow/simple_flow.py
refinire/agents/flow/step.py
refinire/agents/pipeline/__init__.py
refinire/agents/pipeline/llm_pipeline.py
refinire/agents/providers/__init__.py
refinire/agents/providers/conversation_history.py
refinire/agents/providers/cut_context.py
refinire/agents/providers/fixed_file.py
refinire/agents/providers/source_code.py
refinire/core/__init__.py
refinire/core/anthropic.py
refinire/core/exceptions.py
refinire/core/gemini.py
refinire/core/llm.py
refinire/core/message.py
refinire/core/model_parser.py
refinire/core/ollama.py
refinire/core/opentelemetry_tracing.py
refinire/core/prompt_store.py
refinire/core/routing.py
refinire/core/trace_context.py
refinire/core/trace_registry.py
refinire/core/tracing.py
refinire-0.3.2.dist-info/METADATA
refinire-0.3.2.dist-info/WHEEL
refinire-0.3.2.dist-info/entry_points.txt
refinire-0.3.2.dist-info/licenses/LICENSE
refinire-0.3.2.dist-info/RECORD
