Metadata-Version: 2.4
Name: refinire
Version: 0.3.2
Summary: Refined simplicity for AI agents - Build intelligent workflows with automatic quality assurance and multi-provider LLM support
Project-URL: Homepage, https://github.com/kitfactory/refinire
Project-URL: Documentation, https://kitfactory.github.io/refinire/
Project-URL: Repository, https://github.com/kitfactory/refinire
Project-URL: Bug-Tracker, https://github.com/kitfactory/refinire/issues
Author-email: Kitfactory <kitfactory@gmail.com>
License: MIT
License-File: LICENSE
Keywords: agents,ai,llm,orchestration,workflow
Classifier: Development Status :: 4 - Beta
Classifier: Intended Audience :: Developers
Classifier: License :: OSI Approved :: MIT License
Classifier: Programming Language :: Python :: 3
Classifier: Programming Language :: Python :: 3.10
Classifier: Programming Language :: Python :: 3.11
Classifier: Programming Language :: Python :: 3.12
Classifier: Topic :: Scientific/Engineering :: Artificial Intelligence
Classifier: Topic :: Software Development :: Libraries :: Python Modules
Requires-Python: >=3.10
Requires-Dist: httpx>=0.24.0
Requires-Dist: nest-asyncio>=1.5.0
Requires-Dist: oneenv
Requires-Dist: openai-agents>=0.0.17
Requires-Dist: pydantic>=2.0.0
Provides-Extra: all
Requires-Dist: anthropic>=0.34.0; extra == 'all'
Requires-Dist: google-generativeai>=0.3.0; extra == 'all'
Requires-Dist: ollama>=0.1.0; extra == 'all'
Requires-Dist: openinference-instrumentation; extra == 'all'
Requires-Dist: openinference-instrumentation-openai; extra == 'all'
Requires-Dist: opentelemetry-exporter-otlp; extra == 'all'
Requires-Dist: rich>=13.0.0; extra == 'all'
Provides-Extra: anthropic
Requires-Dist: anthropic>=0.34.0; extra == 'anthropic'
Provides-Extra: cli
Requires-Dist: rich>=13.0.0; extra == 'cli'
Provides-Extra: dev
Requires-Dist: colorama>=0.4.6; extra == 'dev'
Requires-Dist: mkdocs-material>=9.6.14; extra == 'dev'
Requires-Dist: mkdocstrings-python>=1.16.10; extra == 'dev'
Requires-Dist: mkdocstrings>=0.29.1; extra == 'dev'
Requires-Dist: mypy>=1.10.0; extra == 'dev'
Requires-Dist: pydantic>=2.0.0; extra == 'dev'
Requires-Dist: pytest-asyncio>=0.26.0; extra == 'dev'
Requires-Dist: pytest-cov>=4.1.0; extra == 'dev'
Requires-Dist: pytest>=8.0.0; extra == 'dev'
Provides-Extra: google
Requires-Dist: google-generativeai>=0.3.0; extra == 'google'
Provides-Extra: ollama
Requires-Dist: ollama>=0.1.0; extra == 'ollama'
Provides-Extra: openinference-instrumentation
Requires-Dist: openinference-instrumentation; extra == 'openinference-instrumentation'
Requires-Dist: openinference-instrumentation-openai; extra == 'openinference-instrumentation'
Requires-Dist: opentelemetry-exporter-otlp; extra == 'openinference-instrumentation'
